{
    "docs": {
        "overview.md": {
            "description": "An introduction to the API and its features."
        },
        "getting-started.md": {
            "description": "A guide on how to set up and start using the API."
        },
        "endpoints": [
            {
                "code_name": "app/routes/auth.routes.js"
            },
            {
                "code_name": "app/routes/catbot.routes.js"
            },
            {
                "code_name": "app/routes/console.routes.js"
            },
            {
                "code_name": "app/routes/contact.routes.js"
            },
            {
                "code_name": "app/routes/fact.routes.js"
            },
            {
                "code_name": "app/routes/index.js"
            },
            {
                "code_name": "app/routes/recipient.routes.js"
            },
            {
                "code_name": "app/routes/user.routes.js"
            },
            {
                "code_name": "app/routes/webhook.routes.js"
            }
        ],
        "models": [
            {
                "code_name": "app/models/api-log.js"
            },
            {
                "code_name": "app/models/fact.js"
            },
            {
                "code_name": "app/models/message.js"
            },
            {
                "code_name": "app/models/recipient.js"
            },
            {
                "code_name": "app/models/unsubscribe-date.js"
            },
            {
                "code_name": "app/models/user.js"
            },
            {
                "code_name": "app/models/verification-code.js"
            }
        ],
        "examples": {
            "examples.md": {
                "description": "An example of how to using the API",
                "code_files": []
            }
        }
    }
}